{
  "name": "b3c4d5e6-3333-4bbb-cccc-300000000003",
  "displayName": "Readback Rejection - Inline Correction",
  "description": "User provides party size, agent reads back, user corrects the value. Tests setter overwrite of pending value (no reject_pending needed), then re-readback and confirm.",
  "tags": [
    "slot-machine",
    "readback",
    "correction",
    "critical"
  ],
  "evaluationDatasets": [
    "Bella Notte Slot Machine - Full Suite"
  ],
  "golden": {
    "turns": [
      {
        "steps": [
          {
            "userInput": {
              "text": "Table for 3 please"
            }
          },
          {
            "expectation": {
              "note": "Check_SetPartySize_Called",
              "toolCall": {
                "tool": "set_reservation_basics",
                "args": {
                  "party_size": 3.0
                }
              }
            }
          },
          {
            "expectation": {
              "note": "Check_PartySize_Pending",
              "updatedVariables": {
                "sm": {
                  "pending": {
                    "party_size": 3
                  }
                }
              }
            }
          }
        ]
      },
      {
        "steps": [
          {
            "userInput": {
              "text": "Actually no, make it 4 people"
            }
          },
          {
            "expectation": {
              "note": "Check_SetPartySize_Corrected",
              "toolCall": {
                "tool": "set_reservation_basics",
                "args": {
                  "party_size": 4.0
                }
              }
            }
          },
          {
            "expectation": {
              "note": "Check_Corrected_Pending",
              "updatedVariables": {
                "sm": {
                  "pending": {
                    "party_size": 4
                  }
                }
              }
            }
          }
        ]
      },
      {
        "steps": [
          {
            "userInput": {
              "text": "Yes, that's right"
            }
          },
          {
            "expectation": {
              "note": "Check_PartySize_Confirmed",
              "updatedVariables": {
                "sm": {
                  "filled": {
                    "party_size": 4
                  },
                  "pending": {}
                }
              }
            }
          }
        ]
      }
    ],
    "evaluationExpectations": [
      "No Technical Leakage"
    ]
  }
}
