{
  "name": "df9fba3a-4f86-4070-9805-af164f9ffd7f",
  "displayName": "Deferred Readback - Name And Requests Together Triggers Group",
  "description": "User provides both name and special requests in a single message. Both are inputs to BookReservation (readback_inputs: True), so the group completes immediately and a single combined readback fires — one confirmation instead of two. Verifies that the deferred readback group fires as soon as all members are pending, even when collected simultaneously.",
  "tags": ["slot-machine", "readback", "deferred-readback", "group-readback", "multi-slot", "critical"],
  "golden": {
    "turns": [{
      "steps": [{
        "userInput": {
          "text": "Table for 4 on June 25th"
        }
      }, {
        "expectation": {
          "note": "Check_SetPartySize_Called",
          "toolCall": {
            "tool": "set_party_size",
            "args": {
              "size": 4.0
            }
          }
        }
      }, {
        "expectation": {
          "note": "Check_SetPreferredDate_Called",
          "toolCall": {
            "tool": "set_preferred_date",
            "args": {
              "date": "2026-06-25"
            }
          }
        }
      }, {
        "expectation": {
          "note": "Check_Readback_Size_And_Date",
          "agentResponse": {
            "chunks": [{
              "text": "4"
            }]
          }
        }
      }]
    }, {
      "steps": [{
        "userInput": {
          "text": "Yes"
        }
      }, {
        "expectation": {
          "note": "Check_Times_Shown",
          "agentResponse": {
            "chunks": [{
              "text": "8:30 PM"
            }]
          }
        }
      }]
    }, {
      "steps": [{
        "userInput": {
          "text": "8:30 please"
        }
      }, {
        "expectation": {
          "note": "Check_SetSelectedTime_Called",
          "toolCall": {
            "tool": "set_selected_time"
          }
        }
      }, {
        "expectation": {
          "note": "Check_Readback_Time",
          "agentResponse": {
            "chunks": [{
              "text": "8:30"
            }]
          }
        }
      }]
    }, {
      "steps": [{
        "userInput": {
          "text": "Yes"
        }
      }, {
        "expectation": {
          "note": "Check_Asks_For_Name",
          "agentResponse": {
            "chunks": [{
              "text": "name"
            }]
          }
        }
      }]
    }, {
      "steps": [{
        "userInput": {
          "text": "It's Lee, and we'd like a booth if possible"
        }
      }, {
        "expectation": {
          "note": "Check_SetGuestName_Called",
          "toolCall": {
            "tool": "set_guest_name",
            "args": {
              "name": "Lee"
            }
          }
        }
      }, {
        "expectation": {
          "note": "Check_SetSpecialRequests_Called",
          "toolCall": {
            "tool": "set_special_requests"
          }
        }
      }, {
        "expectation": {
          "note": "Check_Combined_Readback_Name",
          "agentResponse": {
            "chunks": [{
              "text": "Lee"
            }]
          }
        }
      }, {
        "expectation": {
          "note": "Check_Combined_Readback_Requests",
          "agentResponse": {
            "chunks": [{
              "text": "booth"
            }]
          }
        }
      }]
    }, {
      "steps": [{
        "userInput": {
          "text": "Perfect, yes"
        }
      }, {
        "expectation": {
          "note": "Check_Booking_Confirmed",
          "agentResponse": {
            "chunks": [{
              "text": "BN-"
            }]
          }
        }
      }]
    }],
    "evaluationExpectations": ["Warm Restaurant Host Persona", "Tool-Truth - Uses Exact System Values", "No Technical Leakage"]
  }
}
